sslpsk2/__init__.py
sslpsk2/_sslpsk2.cp310-win_amd64.pyd
sslpsk2/libcrypto-3-x64.dll
sslpsk2/libssl-3-x64.dll
sslpsk2/sslpsk2.py
sslpsk2/test/__init__.py
sslpsk2/test/__main__.py
sslpsk2/test/example_client.py
sslpsk2/test/example_server.py
sslpsk2/test/test_sslpsk.py
sslpsk2-1.0.2.dist-info/LICENSE
sslpsk2-1.0.2.dist-info/METADATA
sslpsk2-1.0.2.dist-info/NOTICE
sslpsk2-1.0.2.dist-info/WHEEL
sslpsk2-1.0.2.dist-info/top_level.txt
sslpsk2-1.0.2.dist-info/RECORD
