Metadata-Version: 2.1
Name: sslpsk2
Version: 1.0.2
Summary: Adds TLS-PSK support to the Python ssl package
Home-page: https://github.com/autinerd/sslpsk2
Author: Sidney Kuyateh
Author-email: sidneyjohn23@kuyateh.eu
License: Apache 2.0
Keywords: ssl,tls,psk,tls-psk,preshared key
Platform: UNKNOWN
Classifier: Development Status :: 5 - Production/Stable
Classifier: Intended Audience :: Developers
Classifier: License :: OSI Approved :: Apache Software License
Classifier: Programming Language :: Python
Classifier: Programming Language :: Python :: 2
Classifier: Programming Language :: Python :: 2.7
Classifier: Programming Language :: Python :: 3
Classifier: Programming Language :: Python :: 3.4
Classifier: Programming Language :: Python :: 3.5
Classifier: Programming Language :: Python :: 3.6
Classifier: Programming Language :: Python :: 3.7
Classifier: Programming Language :: Python :: 3.8
Classifier: Programming Language :: Python :: 3.9
Classifier: Programming Language :: Python :: 3.10
Classifier: Programming Language :: Python :: Implementation :: CPython
Classifier: Operating System :: POSIX
Classifier: Operating System :: Unix
Classifier: Operating System :: MacOS
Classifier: Operating System :: Microsoft
License-File: LICENSE
License-File: NOTICE
